aiohttp_admin2/__init__.py
aiohttp_admin2/connection_injectors.py
aiohttp_admin2/controllers/__init__.py
aiohttp_admin2/controllers/controller.py
aiohttp_admin2/controllers/exceptions.py
aiohttp_admin2/controllers/mongo_controller.py
aiohttp_admin2/controllers/mysql_controller.py
aiohttp_admin2/controllers/postgres_controller.py
aiohttp_admin2/controllers/relations.py
aiohttp_admin2/controllers/types.py
aiohttp_admin2/exceptions.py
aiohttp_admin2/mappers/__init__.py
aiohttp_admin2/mappers/base.py
aiohttp_admin2/mappers/exceptions.py
aiohttp_admin2/mappers/fields/__init__.py
aiohttp_admin2/mappers/fields/abc.py
aiohttp_admin2/mappers/fields/array_field.py
aiohttp_admin2/mappers/fields/bolean_field.py
aiohttp_admin2/mappers/fields/choice_field.py
aiohttp_admin2/mappers/fields/date_field.py
aiohttp_admin2/mappers/fields/float_field.py
aiohttp_admin2/mappers/fields/int_field.py
aiohttp_admin2/mappers/fields/json_field.py
aiohttp_admin2/mappers/fields/mongo_fields.py
aiohttp_admin2/mappers/fields/string_field.py
aiohttp_admin2/mappers/fields/url_field.py
aiohttp_admin2/mappers/generics/__init__.py
aiohttp_admin2/mappers/generics/mongo.py
aiohttp_admin2/mappers/validators/__init__.py
aiohttp_admin2/mappers/validators/length.py
aiohttp_admin2/mappers/validators/required.py
aiohttp_admin2/resources/__init__.py
aiohttp_admin2/resources/abc.py
aiohttp_admin2/resources/dict_resource/__init__.py
aiohttp_admin2/resources/dict_resource/dict_resource.py
aiohttp_admin2/resources/dict_resource/filters.py
aiohttp_admin2/resources/exceptions.py
aiohttp_admin2/resources/mongo_resource/__init__.py
aiohttp_admin2/resources/mongo_resource/filters.py
aiohttp_admin2/resources/mongo_resource/mongo_resource.py
aiohttp_admin2/resources/mysql_resource/__init__.py
aiohttp_admin2/resources/mysql_resource/mysql_resource.py
aiohttp_admin2/resources/postgres_resource/__init__.py
aiohttp_admin2/resources/postgres_resource/filters.py
aiohttp_admin2/resources/postgres_resource/postgres_resource.py
aiohttp_admin2-0.0.19.dist-info/AUTHORS.rst
aiohttp_admin2-0.0.19.dist-info/LICENSE
aiohttp_admin2-0.0.19.dist-info/METADATA
aiohttp_admin2-0.0.19.dist-info/WHEEL
aiohttp_admin2-0.0.19.dist-info/RECORD
