Metadata-Version: 2.3
Name: aiohttp_admin2
Version: 0.0.19
Summary: Generator an admin interface based on aiohttp.
License: MIT
Keywords: aiohttp_admin2,admin interface,aiohttp
Author: Mykhailo Havelia
Author-email: misha.gavela@gmail.com
Maintainer: Mykhailo Havelia
Maintainer-email: misha.gavela@gmail.com
Requires-Python: >=3.12.0,<4.0.0
Classifier: License :: OSI Approved :: MIT License
Classifier: Programming Language :: Python :: 3
Classifier: Programming Language :: Python :: 3.12
Classifier: Programming Language :: Python :: 3.13
Provides-Extra: motor
Provides-Extra: mysql
Requires-Dist: aiohttp (>=3.6.3,<4.0.0)
Requires-Dist: aiohttp-jinja2 (>=1.4.2,<2.0.0)
Requires-Dist: aiomysql (==0.2.0) ; extra == "mysql"
Requires-Dist: aiopg[sa] (==1.5.0a1)
Requires-Dist: python-dateutil (>=2.9.0,<3.0.0)
Requires-Dist: sqlalchemy (>=2.0.42,<3.0.0)
Requires-Dist: umongo[motor] (>=3.1.0,<4.0.0) ; extra == "motor"
Project-URL: Documentation, https://aiohttp-admin2.readthedocs.io
Project-URL: Homepage, https://github.com/arfey/aiohttp_admin2
Project-URL: Repository, https://github.com/arfey/aiohttp_admin2
